odoo9_addon_delivery_roulier_dpd-9.0.2.0.0.99.dev5-py3.8-nspkg.pth
odoo_addons/delivery_roulier_dpd/README.rst
odoo_addons/delivery_roulier_dpd/__init__.py
odoo_addons/delivery_roulier_dpd/__openerp__.py
odoo_addons/delivery_roulier_dpd/data/delivery.xml
odoo_addons/delivery_roulier_dpd/data/keychain.xml
odoo_addons/delivery_roulier_dpd/i18n/ca.po
odoo_addons/delivery_roulier_dpd/i18n/cs_CZ.po
odoo_addons/delivery_roulier_dpd/i18n/de.po
odoo_addons/delivery_roulier_dpd/i18n/delivery_roulier_dpd.pot
odoo_addons/delivery_roulier_dpd/i18n/es.po
odoo_addons/delivery_roulier_dpd/i18n/fr.po
odoo_addons/delivery_roulier_dpd/i18n/gl.po
odoo_addons/delivery_roulier_dpd/i18n/it.po
odoo_addons/delivery_roulier_dpd/i18n/nl.po
odoo_addons/delivery_roulier_dpd/i18n/pt_BR.po
odoo_addons/delivery_roulier_dpd/i18n/ro.po
odoo_addons/delivery_roulier_dpd/i18n/sl.po
odoo_addons/delivery_roulier_dpd/models/__init__.py
odoo_addons/delivery_roulier_dpd/models/delivery.py
odoo_addons/delivery_roulier_dpd/models/keychain.py
odoo_addons/delivery_roulier_dpd/models/stock_picking.py
odoo_addons/delivery_roulier_dpd/models/stock_quant_package.py
odoo_addons/delivery_roulier_dpd/static/description/icon.png
odoo9_addon_delivery_roulier_dpd-9.0.2.0.0.99.dev5.dist-info/METADATA
odoo9_addon_delivery_roulier_dpd-9.0.2.0.0.99.dev5.dist-info/WHEEL
odoo9_addon_delivery_roulier_dpd-9.0.2.0.0.99.dev5.dist-info/namespace_packages.txt
odoo9_addon_delivery_roulier_dpd-9.0.2.0.0.99.dev5.dist-info/top_level.txt
odoo9_addon_delivery_roulier_dpd-9.0.2.0.0.99.dev5.dist-info/RECORD
