Metadata-Version: 2.1
Name: odoo9-addon-delivery-roulier-dpd
Version: 9.0.2.0.0.99.dev5
Summary: Generate Labels for DPD
Home-page: http://www.akretion.com/
Author: Akretion, Odoo Community Association (OCA)
Author-email: support@odoo-community.org
License: AGPL-3
Platform: UNKNOWN
Classifier: Programming Language :: Python
Classifier: Framework :: Odoo
Classifier: Framework :: Odoo :: 9.0
Classifier: License :: OSI Approved :: GNU Affero General Public License v3
Requires-Python: ~=2.7
Requires-Dist: cerberus
Requires-Dist: odoo9-addon-delivery-roulier
Requires-Dist: odoo (<9.1a,>=9.0a)
